{
  "header" : "//div/div/div/h3",
  "header1": "//h3",
  "paragraph": "//p",
  "label": ".ant-form-item-required",
  "story": ".ant-select-selector",
  "storyPlaceholder": ".ant-select-selection-placeholder",
  "labelImage": "//label[@title= '5. Upload an image (optional)']",
  "image": ".ant-upload",
  "imagePlaceholder": "//span[@class='ant-upload']//div/div",
  "imageInput": ".ant-upload input",
  "submit": ".ant-btn",
  "submitName": "//button/span",
  "picture" : ".ant-upload-list-item-name",
  "name" : "#name",
  "gender" : ".ant-radio",
  "he": "//div[@id='gender']//span[.='he']",
  "she": "//div[@id='gender']//span[.='she']",
  "it": "//div[@id='gender']//span[.='it']",
  "age" : "#age",
  "spinUp" : ".ant-input-number-handler-up-inner",
  "spinDown" : ".ant-input-number-handler-down-inner",
  "storyField": ".ant-select",
  "typeOfStoryClick" : ".ant-select-item-option-content",
  "tryAgain" : ".btn-primary",
  "text" : ".card-text",
  "storyHeader" : ".mb-4",
  "storyChoice" : ".ant-select-item-option-content",
  "create" : ".ant-btn",
  "dropdownTOS":".ant-select-item-option-content",
  "pictureAddHidden": "//input[@type=\"file\"]",
  "deleteImage": ".anticon-delete",
  "picturePreview": ".ant-upload-list-item-info",
  "pictureFinal": "//img[@src]",
  "errorPicture": "/static/error.86e8f937.png",
  "testPicture": "testtwo.png"
}


